<?xml version="1.0" encoding="utf-8"?>
<annotation>
   <folder>DBMI</folder>
   <filename>img_26.jpg</filename>
   <size>
      <width>813</width>
      <height>360</height>
      <depth>3</depth>
   </size>
   <object>
      <name>Braille</name>
      <pose>Rear</pose>
      <truncated>0</truncated>
      <difficult>0</difficult>
      <bndbox>
         <xmin>37</xmin>
         <xmax>59</xmax>
         <ymin>120</ymin>
         <ymax>150</ymax>
      </bndbox>
   </object>
   <object>
      <name>Braille</name>
      <pose>Rear</pose>
      <truncated>0</truncated>
      <difficult>0</difficult>
      <bndbox>
         <xmin>36</xmin>
         <xmax>57</xmax>
         <ymin>236</ymin>
         <ymax>265</ymax>
      </bndbox>
   </object>
   <object>
      <name>Braille</name>
      <pose>Rear</pose>
      <truncated>0</truncated>
      <difficult>0</difficult>
      <bndbox>
         <xmin>194</xmin>
         <xmax>214</xmax>
         <ymin>237</ymin>
         <ymax>266</ymax>
      </bndbox>
   </object>
   <object>
      <name>Braille</name>
      <pose>Rear</pose>
      <truncated>0</truncated>
      <difficult>0</difficult>
      <bndbox>
         <xmin>194</xmin>
         <xmax>214</xmax>
         <ymin>120</ymin>
         <ymax>149</ymax>
      </bndbox>
   </object>
   <object>
      <name>Braille</name>
      <pose>Rear</pose>
      <truncated>0</truncated>
      <difficult>0</difficult>
      <bndbox>
         <xmin>362</xmin>
         <xmax>382</xmax>
         <ymin>121</ymin>
         <ymax>150</ymax>
      </bndbox>
   </object>
   <object>
      <name>Braille</name>
      <pose>Rear</pose>
      <truncated>0</truncated>
      <difficult>0</difficult>
      <bndbox>
         <xmin>521</xmin>
         <xmax>542</xmax>
         <ymin>120</ymin>
         <ymax>150</ymax>
      </bndbox>
   </object>
</annotation>