<?xml version="1.0" encoding="utf-8"?>
<annotation>
   <folder>DBMI</folder>
   <filename>img_49.jpg</filename>
   <size>
      <width>502</width>
      <height>698</height>
      <depth>3</depth>
   </size>
   <object>
      <name>Braille</name>
      <pose>Rear</pose>
      <truncated>0</truncated>
      <difficult>0</difficult>
      <bndbox>
         <xmin>57</xmin>
         <xmax>103</xmax>
         <ymin>130</ymin>
         <ymax>200</ymax>
      </bndbox>
   </object>
   <object>
      <name>Braille</name>
      <pose>Rear</pose>
      <truncated>0</truncated>
      <difficult>0</difficult>
      <bndbox>
         <xmin>118</xmin>
         <xmax>163</xmax>
         <ymin>130</ymin>
         <ymax>200</ymax>
      </bndbox>
   </object>
   <object>
      <name>Braille</name>
      <pose>Rear</pose>
      <truncated>0</truncated>
      <difficult>0</difficult>
      <bndbox>
         <xmin>177</xmin>
         <xmax>224</xmax>
         <ymin>131</ymin>
         <ymax>202</ymax>
      </bndbox>
   </object>
   <object>
      <name>Braille</name>
      <pose>Rear</pose>
      <truncated>0</truncated>
      <difficult>0</difficult>
      <bndbox>
         <xmin>236</xmin>
         <xmax>281</xmax>
         <ymin>130</ymin>
         <ymax>204</ymax>
      </bndbox>
   </object>
   <object>
      <name>Braille</name>
      <pose>Rear</pose>
      <truncated>0</truncated>
      <difficult>0</difficult>
      <bndbox>
         <xmin>60</xmin>
         <xmax>102</xmax>
         <ymin>433</ymin>
         <ymax>502</ymax>
      </bndbox>
   </object>
   <object>
      <name>Braille</name>
      <pose>Rear</pose>
      <truncated>0</truncated>
      <difficult>0</difficult>
      <bndbox>
         <xmin>120</xmin>
         <xmax>163</xmax>
         <ymin>434</ymin>
         <ymax>505</ymax>
      </bndbox>
   </object>
   <object>
      <name>Braille</name>
      <pose>Rear</pose>
      <truncated>0</truncated>
      <difficult>0</difficult>
      <bndbox>
         <xmin>182</xmin>
         <xmax>221</xmax>
         <ymin>436</ymin>
         <ymax>506</ymax>
      </bndbox>
   </object>
   <object>
      <name>Braille</name>
      <pose>Rear</pose>
      <truncated>0</truncated>
      <difficult>0</difficult>
      <bndbox>
         <xmin>237</xmin>
         <xmax>280</xmax>
         <ymin>439</ymin>
         <ymax>510</ymax>
      </bndbox>
   </object>
</annotation>