<?xml version="1.0" encoding="utf-8"?>
<annotation>
   <folder>DBMI</folder>
   <filename>img_3.jpg</filename>
   <size>
      <width>500</width>
      <height>478</height>
      <depth>3</depth>
   </size>
   <object>
      <name>Braille</name>
      <pose>Rear</pose>
      <truncated>0</truncated>
      <difficult>0</difficult>
      <bndbox>
         <xmin>188</xmin>
         <xmax>213</xmax>
         <ymin>249</ymin>
         <ymax>286</ymax>
      </bndbox>
   </object>
   <object>
      <name>Braille</name>
      <pose>Rear</pose>
      <truncated>0</truncated>
      <difficult>0</difficult>
      <bndbox>
         <xmin>223</xmin>
         <xmax>248</xmax>
         <ymin>248</ymin>
         <ymax>287</ymax>
      </bndbox>
   </object>
   <object>
      <name>Braille</name>
      <pose>Rear</pose>
      <truncated>0</truncated>
      <difficult>0</difficult>
      <bndbox>
         <xmin>259</xmin>
         <xmax>282</xmax>
         <ymin>249</ymin>
         <ymax>284</ymax>
      </bndbox>
   </object>
   <object>
      <name>Braille</name>
      <pose>Rear</pose>
      <truncated>0</truncated>
      <difficult>0</difficult>
      <bndbox>
         <xmin>294</xmin>
         <xmax>319</xmax>
         <ymin>247</ymin>
         <ymax>284</ymax>
      </bndbox>
   </object>
</annotation>