<?xml version="1.0" encoding="utf-8"?>
<annotation>
   <folder>DBMI</folder>
   <filename>img_180.jpg</filename>
   <size>
      <width>4032</width>
      <height>3024</height>
      <depth>3</depth>
   </size>
   <object>
      <name>Braille</name>
      <pose>Rear</pose>
      <truncated>0</truncated>
      <difficult>0</difficult>
      <bndbox>
         <xmin>1157</xmin>
         <xmax>1254</xmax>
         <ymin>268</ymin>
         <ymax>425</ymax>
      </bndbox>
   </object>
   <object>
      <name>Braille</name>
      <pose>Rear</pose>
      <truncated>0</truncated>
      <difficult>0</difficult>
      <bndbox>
         <xmin>1282</xmin>
         <xmax>1361</xmax>
         <ymin>268</ymin>
         <ymax>425</ymax>
      </bndbox>
   </object>
   <object>
      <name>Braille</name>
      <pose>Rear</pose>
      <truncated>0</truncated>
      <difficult>0</difficult>
      <bndbox>
         <xmin>2044</xmin>
         <xmax>2115</xmax>
         <ymin>2600</ymin>
         <ymax>2731</ymax>
      </bndbox>
   </object>
   <object>
      <name>Braille</name>
      <pose>Rear</pose>
      <truncated>0</truncated>
      <difficult>0</difficult>
      <bndbox>
         <xmin>2274</xmin>
         <xmax>2354</xmax>
         <ymin>2600</ymin>
         <ymax>2736</ymax>
      </bndbox>
   </object>
   <object>
      <name>Braille</name>
      <pose>Rear</pose>
      <truncated>0</truncated>
      <difficult>0</difficult>
      <bndbox>
         <xmin>2374</xmin>
         <xmax>2456</xmax>
         <ymin>2608</ymin>
         <ymax>2746</ymax>
      </bndbox>
   </object>
   <object>
      <name>Braille</name>
      <pose>Rear</pose>
      <truncated>0</truncated>
      <difficult>0</difficult>
      <bndbox>
         <xmin>2482</xmin>
         <xmax>2567</xmax>
         <ymin>2608</ymin>
         <ymax>2749</ymax>
      </bndbox>
   </object>
   <object>
      <name>Braille</name>
      <pose>Rear</pose>
      <truncated>0</truncated>
      <difficult>0</difficult>
      <bndbox>
         <xmin>2590</xmin>
         <xmax>2677</xmax>
         <ymin>2608</ymin>
         <ymax>2744</ymax>
      </bndbox>
   </object>
</annotation>